{
  "_binary": { "iconPath": "../assets/file/light/binary.svg" },
  "_binary_dark": { "iconPath": "../assets/file/dark/binary.svg" },

  "_c_h": { "iconPath": "../assets/file/light/c_h.svg" },
  "_c_h_dark": { "iconPath": "../assets/file/dark/c_h.svg" },

  "_c": { "iconPath": "../assets/file/light/c.svg" },
  "_c_dark": { "iconPath": "../assets/file/dark/c.svg" },

  "_clangd": { "iconPath": "../assets/file/light/clangd.svg" },
  "_clangd_dark": { "iconPath": "../assets/file/dark/clangd.svg" },

  "_cmake_debug": { "iconPath": "../assets/file/light/cmake_debug.svg" },
  "_cmake_debug_dark": { "iconPath": "../assets/file/dark/cmake_debug.svg" },

  "_cmake_test": { "iconPath": "../assets/file/light/cmake_test.svg" },
  "_cmake_test_dark": { "iconPath": "../assets/file/dark/cmake_test.svg" },

  "_cmake": { "iconPath": "../assets/file/light/cmake.svg" },
  "_cmake_dark": { "iconPath": "../assets/file/dark/cmake.svg" },

  "_config": { "iconPath": "../assets/file/light/config.svg" },
  "_config_dark": { "iconPath": "../assets/file/dark/config.svg" },

  "_cpp_h": { "iconPath": "../assets/file/light/cpp_h.svg" },
  "_cpp_h_dark": { "iconPath": "../assets/file/dark/cpp_h.svg" },

  "_cpp": { "iconPath": "../assets/file/light/cpp.svg" },
  "_cpp_dark": { "iconPath": "../assets/file/dark/cpp.svg" },

  "_diagram": { "iconPath": "../assets/file/light/diagram.svg" },
  "_diagram_dark": { "iconPath": "../assets/file/dark/diagram.svg" },

  "_docker_compose": { "iconPath": "../assets/file/light/docker_compose.svg" },
  "_docker_compose_dark": { "iconPath": "../assets/file/dark/docker_compose.svg" },

  "_docker_ignore": { "iconPath": "../assets/file/light/docker_ignore.svg" },
  "_docker_ignore_dark": { "iconPath": "../assets/file/dark/docker_ignore.svg" },

  "_docker": { "iconPath": "../assets/file/light/docker.svg" },
  "_docker_dark": { "iconPath": "../assets/file/dark/docker.svg" },

  "_erd_diagram": { "iconPath": "../assets/file/light/erd_diagram.svg" },
  "_erd_diagram_dark": { "iconPath": "../assets/file/dark/erd_diagram.svg" },

  "_eslint": { "iconPath": "../assets/file/light/eslint.svg" },
  "_eslint_dark": { "iconPath": "../assets/file/dark/eslint.svg" },

  "_file": { "iconPath": "../assets/file/light/file.svg" },
  "_file_dark": { "iconPath": "../assets/file/dark/file.svg" },

  "_git": { "iconPath": "../assets/file/light/git.svg" },
  "_git_dark": { "iconPath": "../assets/file/dark/git.svg" },

  "_go_mod": { "iconPath": "../assets/file/light/go_mod.svg" },
  "_go_mod_dark": { "iconPath": "../assets/file/dark/go_mod.svg" },

  "_go_sum": { "iconPath": "../assets/file/light/go_sum.svg" },
  "_go_sum_dark": { "iconPath": "../assets/file/dark/go_sum.svg" },

  "_go_test": { "iconPath": "../assets/file/light/go_test.svg" },
  "_go_test_dark": { "iconPath": "../assets/file/dark/go_test.svg" },

  "_go": { "iconPath": "../assets/file/light/go.svg" },
  "_go_dark": { "iconPath": "../assets/file/dark/go.svg" },

  "_helm_chart": { "iconPath": "../assets/file/light/helm_chart.svg" },
  "_helm_chart_dark": { "iconPath": "../assets/file/dark/helm_chart.svg" },

  "_helm_values": { "iconPath": "../assets/file/light/helm_values.svg" },
  "_helm_values_dark": { "iconPath": "../assets/file/dark/helm_values.svg" },

  "_http": { "iconPath": "../assets/file/light/http.svg" },
  "_http_dark": { "iconPath": "../assets/file/dark/http.svg" },

  "_ignore": { "iconPath": "../assets/file/light/ignore.svg" },
  "_ignore_dark": { "iconPath": "../assets/file/dark/ignore.svg" },

  "_image": { "iconPath": "../assets/file/light/image.svg" },
  "_image_dark": { "iconPath": "../assets/file/dark/image.svg" },

  "_javascript_test": { "iconPath": "../assets/file/light/javascript_test.svg" },
  "_javascript_test_dark": { "iconPath": "../assets/file/dark/javascript_test.svg" },

  "_javascript": { "iconPath": "../assets/file/light/javascript.svg" },
  "_javascript_dark": { "iconPath": "../assets/file/dark/javascript.svg" },

  "_json_schema": { "iconPath": "../assets/file/light/json_schema.svg" },
  "_json_schema_dark": { "iconPath": "../assets/file/dark/json_schema.svg" },

  "_json": { "iconPath": "../assets/file/light/json.svg" },
  "_json_dark": { "iconPath": "../assets/file/dark/json.svg" },

  "_jsonc": { "iconPath": "../assets/file/light/jsonc.svg" },
  "_jsonc_dark": { "iconPath": "../assets/file/dark/jsonc.svg" },

  "_jsx_test": { "iconPath": "../assets/file/light/jsx_test.svg" },
  "_jsx_test_dark": { "iconPath": "../assets/file/dark/jsx_test.svg" },

  "_jsx": { "iconPath": "../assets/file/light/jsx.svg" },
  "_jsx_dark": { "iconPath": "../assets/file/dark/jsx.svg" },

  "_license": { "iconPath": "../assets/file/light/license.svg" },
  "_license_dark": { "iconPath": "../assets/file/dark/license.svg" },

  "_mail": { "iconPath": "../assets/file/light/mail.svg" },
  "_mail_dark": { "iconPath": "../assets/file/dark/mail.svg" },

  "_makefile": { "iconPath": "../assets/file/light/makefile.svg" },
  "_makefile_dark": { "iconPath": "../assets/file/dark/makefile.svg" },

  "_markdown": { "iconPath": "../assets/file/light/markdown.svg" },
  "_markdown_dark": { "iconPath": "../assets/file/dark/markdown.svg" },

  "_prettier": { "iconPath": "../assets/file/light/prettier.svg" },
  "_prettier_dark": { "iconPath": "../assets/file/dark/prettier.svg" },

  "_properties": { "iconPath": "../assets/file/light/properties.svg" },
  "_properties_dark": { "iconPath": "../assets/file/dark/properties.svg" },

  "_proto": { "iconPath": "../assets/file/light/proto.svg" },
  "_proto_dark": { "iconPath": "../assets/file/dark/proto.svg" },

  "_python_test": { "iconPath": "../assets/file/light/python_test.svg" },
  "_python_test_dark": { "iconPath": "../assets/file/dark/python_test.svg" },

  "_python": { "iconPath": "../assets/file/light/python.svg" },
  "_python_dark": { "iconPath": "../assets/file/dark/python.svg" },

  "_shell": { "iconPath": "../assets/file/light/shell.svg" },
  "_shell_dark": { "iconPath": "../assets/file/dark/shell.svg" },

  "_sql": { "iconPath": "../assets/file/light/sql.svg" },
  "_sql_dark": { "iconPath": "../assets/file/dark/sql.svg" },

  "_svg": { "iconPath": "../assets/file/light/svg.svg" },
  "_svg_dark": { "iconPath": "../assets/file/dark/svg.svg" },

  "_tsconfig": { "iconPath": "../assets/file/light/tsconfig.svg" },
  "_tsconfig_dark": { "iconPath": "../assets/file/dark/tsconfig.svg" },

  "_tsx_test": { "iconPath": "../assets/file/light/tsx_test.svg" },
  "_tsx_test_dark": { "iconPath": "../assets/file/dark/tsx_test.svg" },

  "_tsx": { "iconPath": "../assets/file/light/tsx.svg" },
  "_tsx_dark": { "iconPath": "../assets/file/dark/tsx.svg" },

  "_typescript_test": { "iconPath": "../assets/file/light/typescript_test.svg" },
  "_typescript_test_dark": { "iconPath": "../assets/file/dark/typescript_test.svg" },

  "_typescript": { "iconPath": "../assets/file/light/typescript.svg" },
  "_typescript_dark": { "iconPath": "../assets/file/dark/typescript.svg" },

  "_webpack": { "iconPath": "../assets/file/light/webpack.svg" },
  "_webpack_dark": { "iconPath": "../assets/file/dark/webpack.svg" },

  "_xml": { "iconPath": "../assets/file/light/xml.svg" },
  "_xml_dark": { "iconPath": "../assets/file/dark/xml.svg" },

  "_yaml": { "iconPath": "../assets/file/light/yaml.svg" },
  "_yaml_dark": { "iconPath": "../assets/file/dark/yaml.svg" }
}
